scidats/__init__.py
scidats/__main__.py
scidats/metadata_model_scidats_core.py
scidats/metadata_model_scidats_core_context.py
scidats/metadata_model_scidats_dcat_ap.py
scidats/metadata_model_scidats_dcat_ap_context.py
scidats/metadata_model_scidats_dcmi.py
scidats/metadata_model_scidats_dcmi_context.py
scidats/metadata_old.py
scidats/scidats_impl.py
scidats/scidats_interface.py
scidats-0.0.10.dist-info/METADATA
scidats-0.0.10.dist-info/WHEEL
scidats-0.0.10.dist-info/entry_points.txt
scidats-0.0.10.dist-info/licenses/AUTHORS.md
scidats-0.0.10.dist-info/licenses/LICENSE
scidats-0.0.10.dist-info/RECORD
