Metadata-Version: 2.4
Name: scidats
Version: 0.0.10
Summary: SciDatS is a python package for storing and retrieving scientific data stored in JSON-LD (semantically annotated JSON - Linked Data).
Project-URL: Homepage, https://gitlab.com/opensourcelab/scientificdata/scidats
Author-email: mark doerr <mark@uni-greifswald.de>
License: MIT
License-File: AUTHORS.md
License-File: LICENSE
Classifier: Development Status :: 2 - Pre-Alpha
Classifier: Intended Audience :: Developers
Classifier: Intended Audience :: Education
Classifier: Intended Audience :: Science/Research
Classifier: License :: OSI Approved :: MIT License
Classifier: Natural Language :: English
Classifier: Operating System :: OS Independent
Classifier: Programming Language :: Python :: 3
Classifier: Programming Language :: Python :: 3.9
Classifier: Programming Language :: Python :: 3.10
Classifier: Topic :: Scientific/Engineering
Classifier: Topic :: Scientific/Engineering :: Bio-Informatics
Classifier: Topic :: Scientific/Engineering :: Chemistry
Classifier: Topic :: Scientific/Engineering :: Information Analysis
Classifier: Topic :: Scientific/Engineering :: Visualization
Requires-Dist: fastparquet
Requires-Dist: pandas
Requires-Dist: parquet
Requires-Dist: pyarrow
Requires-Dist: pydantic
Requires-Dist: pyld>=2.0.4
Requires-Dist: rdflib
Provides-Extra: dev
Requires-Dist: bandit>=1.0; extra == 'dev'
Requires-Dist: black>=20.0; extra == 'dev'
Requires-Dist: bumpversion>=0.6; extra == 'dev'
Requires-Dist: coverage>=7.2; extra == 'dev'
Requires-Dist: invoke>=2.1; extra == 'dev'
Requires-Dist: isort>=5.0; extra == 'dev'
Requires-Dist: mypy>=0.0; extra == 'dev'
Requires-Dist: pylint>=2.0; extra == 'dev'
Requires-Dist: pyproject-flake8; extra == 'dev'
Requires-Dist: pytest-cov; extra == 'dev'
Requires-Dist: pytest-cov>=2.12; extra == 'dev'
Requires-Dist: pytest-xdist>=2.0; extra == 'dev'
Requires-Dist: pytest>=7.3; extra == 'dev'
Requires-Dist: safety>=1.0; extra == 'dev'
Requires-Dist: tox>=4.5; extra == 'dev'
Provides-Extra: docs
Requires-Dist: linkml>=1.8.2; extra == 'docs'
Requires-Dist: myst-parser>=1.0; extra == 'docs'
Requires-Dist: python-docs-theme>=2023.3; extra == 'docs'
Requires-Dist: sphinx>=7.0; extra == 'docs'
Provides-Extra: test
Requires-Dist: bandit>=1.0; extra == 'test'
Requires-Dist: black>=20.0; extra == 'test'
Requires-Dist: coverage>=7.2; extra == 'test'
Requires-Dist: flake8>=3.0; extra == 'test'
Requires-Dist: isort>=5.0; extra == 'test'
Requires-Dist: mypy>=0.0; extra == 'test'
Requires-Dist: pylint>=2.0; extra == 'test'
Requires-Dist: pytest-cov>=2.12; extra == 'test'
Requires-Dist: pytest-xdist>=2.0; extra == 'test'
Requires-Dist: pytest>=7.3; extra == 'test'
Requires-Dist: safety>=1.0; extra == 'test'
Requires-Dist: tox>=4.5; extra == 'test'
